collate/__init__.py
collate/collate.py
collate/imputations.py
collate/spacetime.py
collate/sql.py
collate-0.3.0.dist-info/DESCRIPTION.rst
collate-0.3.0.dist-info/METADATA
collate-0.3.0.dist-info/RECORD
collate-0.3.0.dist-info/WHEEL
collate-0.3.0.dist-info/metadata.json
collate-0.3.0.dist-info/top_level.txt
