Metadata-Version: 2.0
Name: collate
Version: 0.3.0
Summary: Aggregated feature generation made easy.
Home-page: https://github.com/dssg/collate
Author: DSaPP Researchers
Author-email: datascifellows@gmail.com
License: MIT license
Keywords: collate
Platform: UNKNOWN
Classifier: Development Status :: 2 - Pre-Alpha
Classifier: Intended Audience :: Developers
Classifier: License :: OSI Approved :: MIT License
Classifier: Natural Language :: English
Classifier: Programming Language :: Python :: 2
Classifier: Programming Language :: Python :: 2.6
Classifier: Programming Language :: Python :: 2.7
Classifier: Programming Language :: Python :: 3
Classifier: Programming Language :: Python :: 3.3
Classifier: Programming Language :: Python :: 3.4
Classifier: Programming Language :: Python :: 3.5
